nh5/__init__.py
nh5/h5_to_nh5.py
nh5-0.1.3.dist-info/LICENSE
nh5-0.1.3.dist-info/METADATA
nh5-0.1.3.dist-info/WHEEL
nh5-0.1.3.dist-info/RECORD
