Metadata-Version: 2.1
Name: nh5
Version: 0.1.3
Summary: Utilities to support the nh5 file format
Home-page: https://github.com/magland/nh5
License: Apache-2.0
Author: Jeremy Magland
Requires-Python: >=3.9,<4.0
Classifier: License :: OSI Approved :: Apache Software License
Classifier: Programming Language :: Python :: 3
Classifier: Programming Language :: Python :: 3.9
Classifier: Programming Language :: Python :: 3.10
Classifier: Programming Language :: Python :: 3.11
Classifier: Programming Language :: Python :: 3.12
Requires-Dist: h5py (>=3.10.0,<4.0.0)
Requires-Dist: numpy (>=1.26.3,<2.0.0)
Project-URL: Repository, https://github.com/magland/nh5
